[
  {
    "t_id": 1,
    "t_pid": 0,
    "id": "MEN2",
    "type": "Menu",
    "description": "Menu2",
    "conditional": false,
    "minval": 0,
    "maxval": 0,
    "hidden": false
  },
  {
    "t_id": 2,
    "t_pid": 1,
    "id": "NBF",
    "type": "Type",
    "description": "Normal Lunch",
    "conditional": false,
    "minval": 0,
    "maxval": 0,
    "hidden": false
  },
  {
    "t_id": 8,
    "t_pid": 2,
    "id": "G",
    "type": "Group",
    "description": "Light Meal Option",
    "conditional": true,
    "minval": 0,
    "maxval": 0,
    "field": "",
    "option_id": "",
    "hidden": false
  },
  {
    "t_id": 19,
    "t_pid": 8,
    "id": "S",
    "type": "Subgroup",
    "description": "Sandwich (1 Round)",
    "conditional": true,
    "minval": 0,
    "maxval": 0,
    "field": "",
    "option_id": "",
    "hidden": false
  },
  {
    "t_id": 20,
    "t_pid": 19,
    "id": "FRENCH",
    "type": "Item",
    "description": "French Toast",
    "conditional": true,
    "minval": 0,
    "maxval": 1,
    "field": "formonly.t1g3sg1ch1",
    "option_id": "CHEESE",
    "option_name": "With Cheese",
    "hidden": false
  },
  {
    "t_id": 21,
    "t_pid": 19,
    "id": "EGGSAN",
    "type": "Item",
    "description": "Egg Sandwich",
    "conditional": true,
    "minval": 0,
    "maxval": 1,
    "field": "formonly.t1g3sg1ch2",
    "option_id": "",
    "hidden": false
  },
  {
    "t_id": 22,
    "t_pid": 19,
    "id": "CHKMAY",
    "type": "Item",
    "description": "Chicken & Mayo",
    "conditional": true,
    "minval": 0,
    "maxval": 1,
    "field": "formonly.t1g3sg1ch3",
    "option_id": "",
    "hidden": false
  },
  {
    "t_id": 23,
    "t_pid": 19,
    "id": "CHSTOM",
    "type": "Item",
    "description": "Cheese & Tomato",
    "conditional": true,
    "minval": 0,
    "maxval": 1,
    "field": "formonly.t1g3sg1ch4",
    "option_id": "",
    "hidden": false
  },
  {
    "t_id": 9,
    "t_pid": 2,
    "id": "G",
    "type": "Group",
    "description": "Healthy Meal Option",
    "conditional": true,
    "minval": 0,
    "maxval": 0,
    "field": "",
    "option_id": "",
    "hidden": false
  },
  {
    "t_id": 24,
    "t_pid": 9,
    "id": "S",
    "type": "Subgroup",
    "description": "",
    "conditional": true,
    "minval": 0,
    "maxval": 0,
    "field": "",
    "option_id": "",
    "hidden": true
  },
  {
    "t_id": 25,
    "t_pid": 24,
    "id": "SALAD",
    "type": "Item",
    "description": "A Salad",
    "conditional": false,
    "minval": 0,
    "maxval": 1,
    "field": "formonly.t1g4sg1ch1",
    "option_id": "",
    "hidden": false
  },
  {
    "t_id": 10,
    "t_pid": 2,
    "id": "G",
    "type": "Group",
    "description": "Condiments",
    "conditional": false,
    "minval": 0,
    "maxval": 0,
    "field": "",
    "option_id": "",
    "hidden": false
  },
  {
    "t_id": 26,
    "t_pid": 10,
    "id": "S",
    "type": "Subgroup",
    "description": "",
    "conditional": false,
    "minval": 0,
    "maxval": 0,
    "field": "",
    "option_id": "",
    "hidden": true
  },
  {
    "t_id": 28,
    "t_pid": 26,
    "id": "FIVER",
    "type": "Item",
    "description": "Five Roses Tea",
    "conditional": true,
    "minval": 0,
    "maxval": 1,
    "field": "formonly.t1g5sg1ch1",
    "option_id": "WMILK",
    "option_name": "With Milk",
    "hidden": false
  },
  {
    "t_id": 29,
    "t_pid": 26,
    "id": "ROOIB",
    "type": "Item",
    "description": "Rooibos Tea",
    "conditional": true,
    "minval": 0,
    "maxval": 1,
    "field": "formonly.t1g5sg1ch2",
    "option_id": "WMILK",
    "option_name": "With Milk",
    "hidden": false
  },
  {
    "t_id": 30,
    "t_pid": 26,
    "id": "COFFEE",
    "type": "Item",
    "description": "Coffee",
    "conditional": true,
    "minval": 0,
    "maxval": 1,
    "field": "formonly.t1g5sg1ch3",
    "option_id": "WMILK",
    "option_name": "With Milk",
    "hidden": false
  },
  {
    "t_id": 31,
    "t_pid": 26,
    "id": "JUICE",
    "type": "Item",
    "description": "Juice",
    "conditional": false,
    "minval": 0,
    "maxval": 1,
    "field": "formonly.t1g5sg1ch4",
    "option_id": "",
    "hidden": false
  },
  {
    "t_id": 32,
    "t_pid": 26,
    "id": "CANDER",
    "type": "Item",
    "description": "Canderel",
    "conditional": false,
    "minval": 0,
    "maxval": 2,
    "field": "formonly.t1g5sg1sp5",
    "option_id": "",
    "hidden": false
  },
  {
    "t_id": 33,
    "t_pid": 26,
    "id": "BROWNS",
    "type": "Item",
    "description": "Brown Sugar",
    "conditional": false,
    "minval": 0,
    "maxval": 2,
    "field": "formonly.t1g5sg1sp6",
    "option_id": "",
    "hidden": false
  },
  {
    "t_id": 34,
    "t_pid": 26,
    "id": "WHITES",
    "type": "Item",
    "description": "White Sugar",
    "conditional": false,
    "minval": 0,
    "maxval": 2,
    "field": "formonly.t1g5sg1sp7",
    "option_id": "",
    "hidden": false
  }
]
